stereoid/__init__.py
stereoid/cli.py
stereoid/instrument/__init__.py
stereoid/instrument/dca_performance.py
stereoid/instrument/radar_model.py
stereoid/instrument/tops_model.py
stereoid/land_ice/AASR_code.py
stereoid/land_ice/AASR_functions.py
stereoid/land_ice/__init__.py
stereoid/land_ice/back_scatter_model.py
stereoid/land_ice/coherence_model_SAR_stack.py
stereoid/land_ice/coherence_model_baseline_volume.py
stereoid/land_ice/deterministic_data.py
stereoid/land_ice/forward_model.py
stereoid/land_ice/ice_polarimetry.py
stereoid/land_ice/line_of_sight_vectors_worldwide.py
stereoid/land_ice/phase_model.py
stereoid/land_ice/plot_SAR_vs_models.py
stereoid/land_ice/plot_functions.py
stereoid/land_ice/radar_model.py
stereoid/land_ice/retrieval_model.py
stereoid/land_ice/study_area_plots.py
stereoid/mission/__init__.py
stereoid/mission/acquisitions_script.py
stereoid/mission/activation_analysis.py
stereoid/mission/coverage.py
stereoid/mission/formation_design.py
stereoid/oceans/__init__.py
stereoid/oceans/forward_model.py
stereoid/oceans/l2_covariance.py
stereoid/oceans/profile_add_errors.py
stereoid/oceans/read_fwd.py
stereoid/oceans/retrieval_model.py
stereoid/oceans/retrieval_performance.py
stereoid/oceans/run_scenario.py
stereoid/oceans/sensitivity_distribution.py
stereoid/oceans/forward_models/Doppler.py
stereoid/oceans/forward_models/RIM_calibration.py
stereoid/oceans/forward_models/RIM_constants.py
stereoid/oceans/forward_models/SAR_spectra.py
stereoid/oceans/forward_models/SAR_spectra_broken.py
stereoid/oceans/forward_models/__init__.py
stereoid/oceans/forward_models/backscatter.py
stereoid/oceans/forward_models/backscatter_doppler_tools.py
stereoid/oceans/forward_models/cdop.py
stereoid/oceans/forward_models/cmod5n.py
stereoid/oceans/forward_models/iwrap_backscatter.py
stereoid/oceans/forward_models/sea_state_bias.py
stereoid/oceans/forward_models/spectrum_tools.py
stereoid/oceans/forward_models/wrappers.py
stereoid/oceans/forward_models/zadelhoff_crosspol.py
stereoid-0.4.dist-info/LICENSE
stereoid-0.4.dist-info/METADATA
stereoid-0.4.dist-info/WHEEL
stereoid-0.4.dist-info/entry_points.txt
stereoid-0.4.dist-info/top_level.txt
stereoid-0.4.dist-info/RECORD
