Metadata-Version: 2.1
Name: stereoid
Version: 0.4
Summary: The stereoid tools for the Harmony mission.
Author-email: Paco Lopez Dekker <F.LopezDekker@tudelft.nl>, Andreas Theodosiou <a.theodosiou@tudelft.nl>, Marcel Kleinherenbrink <M.Kleinherenbrink@tudelft.nl>
Project-URL: Repository, https://gitlab.tudelft.nl/drama/stereoid.git
Project-URL: Bug Tracker, https://gitlab.tudelft.nl/drama/stereoid/-/issues
Classifier: Programming Language :: Python :: 3
Classifier: License :: OSI Approved :: GNU General Public License v3 (GPLv3)
Classifier: Operating System :: OS Independent
Classifier: Intended Audience :: Science/Research
Classifier: Topic :: Scientific/Engineering
Requires-Python: >=3.9
License-File: LICENSE
Requires-Dist: numba
Requires-Dist: numpy
Requires-Dist: scipy
Requires-Dist: numexpr >=2.7
Requires-Dist: netcdf4
Requires-Dist: xarray
Requires-Dist: drama >=0.7
Requires-Dist: tqdm
Provides-Extra: carto
Requires-Dist: matplotlib ; extra == 'carto'
Requires-Dist: cartopy ; extra == 'carto'
Provides-Extra: plot
Requires-Dist: matplotlib ; extra == 'plot'
Provides-Extra: spectra
Requires-Dist: wavespectra ; extra == 'spectra'
